{"universe":"healthcare","updated":"2026-06-24T23:42:43.709181+00:00","count":24,"results":[{"ticker":"VRTX","company":"Vertex Pharmaceuticals Incorporated","sector":"Healthcare","current_price":475.2,"change_pct":1.45,"avg_volume":1432156,"scores":{"technical":52,"fundamental":85,"news":0,"composite":54,"mid_term":66},"trade":{"entry":475.2,"stop_loss":439.9298,"stop_pct":7.4,"target_1":485.0,"target_1_pct":2.1,"target_2":487.52,"target_2_pct":2.6,"risk_reward_t1":0.3,"risk_reward_t2":0.3},"indicators":{"rsi":67.3,"above_sma20":true,"above_sma50":true,"macd_bullish":true,"atr":11.7567,"atr_pct":2.47},"fundamentals":{"pe_ratio":28.185053,"revenue_growth":0.078,"profit_margin":0.35507,"analyst_target":548.6896,"analyst_consensus":1.60606},"patterns":["Golden Cross","Double Bottom"],"52w_high":507.92,"52w_low":362.5,"short_squeeze":false,"short_float_pct":2.0},{"ticker":"BSX","company":"Boston Scientific Corporation","sector":"Healthcare","current_price":44.46,"change_pct":-2.5,"avg_volume":24047030,"scores":{"technical":13,"fundamental":96,"news":0,"composite":38,"mid_term":60},"trade":{"entry":44.46,"stop_loss":39.5129,"stop_pct":11.1,"target_1":50.14,"target_1_pct":12.8,"target_2":57.6523,"target_2_pct":29.7,"risk_reward_t1":1.1,"risk_reward_t2":2.7},"indicators":{"rsi":29.7,"above_sma20":false,"above_sma50":false,"macd_bullish":true,"atr":1.649,"atr_pct":3.71},"fundamentals":{"pe_ratio":18.602509,"revenue_growth":0.116,"profit_margin":0.17294,"analyst_target":77.0357,"analyst_consensus":1.51724},"patterns":["MACD Bullish Divergence","Oversold Bounce"],"52w_high":109.5,"52w_low":44.05,"short_squeeze":false,"short_float_pct":3.9},{"ticker":"MDT","company":"Medtronic plc","sector":"Healthcare","current_price":80.13,"change_pct":-0.62,"avg_volume":12351682,"scores":{"technical":35,"fundamental":79,"news":0,"composite":44,"mid_term":57},"trade":{"entry":80.13,"stop_loss":74.5517,"stop_pct":7.0,"target_1":81.75,"target_1_pct":2.0,"target_2":82.83,"target_2_pct":3.4,"risk_reward_t1":0.3,"risk_reward_t2":0.5},"indicators":{"rsi":52.2,"above_sma20":true,"above_sma50":true,"macd_bullish":true,"atr":1.8594,"atr_pct":2.32},"fundamentals":{"pe_ratio":21.482573,"revenue_growth":0.099,"profit_margin":0.13203,"analyst_target":98.0,"analyst_consensus":1.9},"patterns":["MACD Bullish Divergence","Double Bottom"],"52w_high":106.33,"52w_low":73.31,"short_squeeze":false,"short_float_pct":1.3},{"ticker":"AMGN","company":"Amgen Inc.","sector":"Healthcare","current_price":351.43,"change_pct":1.27,"avg_volume":3120114,"scores":{"technical":100,"fundamental":36,"news":0,"composite":62,"mid_term":53},"trade":{"entry":351.43,"stop_loss":325.2613,"stop_pct":7.4,"target_1":358.46,"target_1_pct":2.0,"target_2":359.45,"target_2_pct":2.3,"risk_reward_t1":0.3,"risk_reward_t2":0.3},"indicators":{"rsi":57.5,"above_sma20":true,"above_sma50":true,"macd_bullish":true,"atr":8.7229,"atr_pct":2.48},"fundamentals":{"pe_ratio":24.45581,"revenue_growth":0.058,"profit_margin":0.20955999,"analyst_target":352.7667,"analyst_consensus":2.45714},"patterns":["Golden Cross","Double Bottom"],"52w_high":391.29,"52w_low":269.77,"short_squeeze":false,"short_float_pct":2.2},{"ticker":"TMO","company":"Thermo Fisher Scientific Inc.","sector":"Healthcare","current_price":492.2,"change_pct":4.87,"avg_volume":2351466,"scores":{"technical":16,"fundamental":76,"news":0,"composite":33,"mid_term":49},"trade":{"entry":492.2,"stop_loss":450.2439,"stop_pct":8.5,"target_1":502.39,"target_1_pct":2.1,"target_2":520.58,"target_2_pct":5.8,"risk_reward_t1":0.2,"risk_reward_t2":0.7},"indicators":{"rsi":59.3,"above_sma20":true,"above_sma50":true,"macd_bullish":true,"atr":13.9854,"atr_pct":2.84},"fundamentals":{"pe_ratio":27.029106,"revenue_growth":0.062,"profit_margin":0.15151,"analyst_target":599.1923,"analyst_consensus":1.53571},"patterns":["Golden Cross","Bull Flag"],"52w_high":643.99,"52w_low":398.08,"short_squeeze":false,"short_float_pct":1.3},{"ticker":"REGN","company":"Regeneron Pharmaceuticals, Inc.","sector":"Healthcare","current_price":623.43,"change_pct":0.87,"avg_volume":1236788,"scores":{"technical":-20,"fundamental":86,"news":0,"composite":18,"mid_term":43},"trade":{"entry":623.43,"stop_loss":572.5838,"stop_pct":8.2,"target_1":640.82,"target_1_pct":2.8,"target_2":664.0,"target_2_pct":6.5,"risk_reward_t1":0.3,"risk_reward_t2":0.8},"indicators":{"rsi":45.3,"above_sma20":true,"above_sma50":false,"macd_bullish":true,"atr":16.9487,"atr_pct":2.72},"fundamentals":{"pe_ratio":15.213031,"revenue_growth":0.19,"profit_margin":0.29648,"analyst_target":833.3061,"analyst_consensus":1.72414},"patterns":[],"52w_high":821.11,"52w_low":514.79,"short_squeeze":false,"short_float_pct":3.0},{"ticker":"SYK","company":"Stryker Corporation","sector":"Healthcare","current_price":313.68,"change_pct":1.19,"avg_volume":2707515,"scores":{"technical":9,"fundamental":67,"news":0,"composite":27,"mid_term":42},"trade":{"entry":313.68,"stop_loss":287.6287,"stop_pct":8.3,"target_1":322.87,"target_1_pct":2.9,"target_2":352.8,"target_2_pct":12.5,"risk_reward_t1":0.4,"risk_reward_t2":1.5},"indicators":{"rsi":54.1,"above_sma20":true,"above_sma50":true,"macd_bullish":true,"atr":8.6838,"atr_pct":2.77},"fundamentals":{"pe_ratio":36.263584,"revenue_growth":0.026,"profit_margin":0.13205,"analyst_target":386.8,"analyst_consensus":1.7037},"patterns":["MACD Bullish Divergence"],"52w_high":404.87,"52w_low":281.0,"short_squeeze":false,"short_float_pct":1.7},{"ticker":"DHR","company":"Danaher Corporation","sector":"Healthcare","current_price":188.87,"change_pct":5.53,"avg_volume":4226735,"scores":{"technical":32,"fundamental":52,"news":0,"composite":33,"mid_term":40},"trade":{"entry":188.87,"stop_loss":173.245,"stop_pct":8.3,"target_1":196.5,"target_1_pct":4.0,"target_2":196.75,"target_2_pct":4.2,"risk_reward_t1":0.5,"risk_reward_t2":0.5},"indicators":{"rsi":62.4,"above_sma20":true,"above_sma50":true,"macd_bullish":true,"atr":5.2083,"atr_pct":2.76},"fundamentals":{"pe_ratio":36.673786,"revenue_growth":0.037,"profit_margin":0.14887999,"analyst_target":242.3478,"analyst_consensus":1.46154},"patterns":["Golden Cross","Bull Flag"],"52w_high":242.8,"52w_low":160.93,"short_squeeze":false,"short_float_pct":1.5},{"ticker":"CI","company":"The Cigna Group","sector":"Healthcare","current_price":279.46,"change_pct":-1.28,"avg_volume":1591046,"scores":{"technical":-28,"fundamental":84,"news":0,"composite":14,"mid_term":40},"trade":{"entry":279.46,"stop_loss":258.5801,"stop_pct":7.5,"target_1":285.67,"target_1_pct":2.2,"target_2":288.67,"target_2_pct":3.3,"risk_reward_t1":0.3,"risk_reward_t2":0.4},"indicators":{"rsi":44.8,"above_sma20":false,"above_sma50":false,"macd_bullish":false,"atr":6.96,"atr_pct":2.49},"fundamentals":{"pe_ratio":11.851569,"revenue_growth":0.046,"profit_margin":0.02263,"analyst_target":340.5,"analyst_consensus":1.54167},"patterns":["Double Bottom"],"52w_high":338.89,"52w_low":239.51,"short_squeeze":false,"short_float_pct":2.5},{"ticker":"CVS","company":"CVS Health Corporation","sector":"Healthcare","current_price":101.87,"change_pct":0.3,"avg_volume":8579573,"scores":{"technical":63,"fundamental":32,"news":0,"composite":42,"mid_term":39},"trade":{"entry":101.87,"stop_loss":94.4247,"stop_pct":7.3,"target_1":114.2788,"target_1_pct":12.2,"target_2":121.7241,"target_2_pct":19.5,"risk_reward_t1":1.7,"risk_reward_t2":2.7},"indicators":{"rsi":68.0,"above_sma20":true,"above_sma50":true,"macd_bullish":true,"atr":2.4818,"atr_pct":2.44},"fundamentals":{"pe_ratio":44.679825,"revenue_growth":0.061,"profit_margin":0.00723,"analyst_target":105.3846,"analyst_consensus":1.5},"patterns":[],"52w_high":103.12,"52w_low":58.5,"short_squeeze":false,"short_float_pct":1.4},{"ticker":"LLY","company":"Eli Lilly and Company","sector":"Healthcare","current_price":1117.26,"change_pct":0.92,"avg_volume":3272666,"scores":{"technical":31,"fundamental":45,"news":0,"composite":30,"mid_term":36},"trade":{"entry":1117.26,"stop_loss":1013.4206,"stop_pct":9.3,"target_1":1149.1,"target_1_pct":2.8,"target_2":1182.73,"target_2_pct":5.9,"risk_reward_t1":0.3,"risk_reward_t2":0.6},"indicators":{"rsi":58.1,"above_sma20":true,"above_sma50":true,"macd_bullish":false,"atr":34.6131,"atr_pct":3.1},"fundamentals":{"pe_ratio":39.73186,"revenue_growth":0.555,"profit_margin":0.34986,"analyst_target":1218.7241,"analyst_consensus":1.74194},"patterns":["Bull Flag"],"52w_high":1182.73,"52w_low":623.78,"short_squeeze":false,"short_float_pct":1.1},{"ticker":"BDX","company":"Becton, Dickinson and Company","sector":"Healthcare","current_price":147.77,"change_pct":2.68,"avg_volume":2542662,"scores":{"technical":6,"fundamental":55,"news":0,"composite":21,"mid_term":34},"trade":{"entry":147.77,"stop_loss":135.7374,"stop_pct":8.1,"target_1":150.74,"target_1_pct":2.0,"target_2":152.0676,"target_2_pct":2.9,"risk_reward_t1":0.2,"risk_reward_t2":0.4},"indicators":{"rsi":52.8,"above_sma20":true,"above_sma50":true,"macd_bullish":false,"atr":4.0109,"atr_pct":2.71},"fundamentals":{"pe_ratio":25.788832,"revenue_growth":0.052,"profit_margin":0.05124,"analyst_target":177.75,"analyst_consensus":2.14286},"patterns":["MACD Bullish Divergence","Double Bottom"],"52w_high":187.35,"52w_low":127.5865,"short_squeeze":false,"short_float_pct":3.0},{"ticker":"JNJ","company":"Johnson & Johnson","sector":"Healthcare","current_price":241.0,"change_pct":0.8,"avg_volume":8446341,"scores":{"technical":52,"fundamental":26,"news":0,"composite":35,"mid_term":32},"trade":{"entry":241.0,"stop_loss":225.8814,"stop_pct":6.3,"target_1":246.35,"target_1_pct":2.2,"target_2":247.21,"target_2_pct":2.6,"risk_reward_t1":0.4,"risk_reward_t2":0.4},"indicators":{"rsi":61.4,"above_sma20":true,"above_sma50":true,"macd_bullish":true,"atr":5.0395,"atr_pct":2.09},"fundamentals":{"pe_ratio":27.92584,"revenue_growth":0.099,"profit_margin":0.21834,"analyst_target":257.3182,"analyst_consensus":2.0},"patterns":["Golden Cross","Double Bottom"],"52w_high":251.71,"52w_low":150.73,"short_squeeze":false,"short_float_pct":1.1},{"ticker":"MRK","company":"Merck & Co., Inc.","sector":"Healthcare","current_price":120.6,"change_pct":0.84,"avg_volume":12207866,"scores":{"technical":71,"fundamental":14,"news":0,"composite":40,"mid_term":31},"trade":{"entry":120.6,"stop_loss":110.8352,"stop_pct":8.1,"target_1":123.13,"target_1_pct":2.1,"target_2":123.33,"target_2_pct":2.3,"risk_reward_t1":0.3,"risk_reward_t2":0.3},"indicators":{"rsi":59.4,"above_sma20":true,"above_sma50":true,"macd_bullish":true,"atr":3.2549,"atr_pct":2.7},"fundamentals":{"pe_ratio":33.971832,"revenue_growth":0.049,"profit_margin":0.13586001,"analyst_target":130.1111,"analyst_consensus":1.82759},"patterns":["Golden Cross"],"52w_high":125.14,"52w_low":76.66,"short_squeeze":false,"short_float_pct":1.2},{"ticker":"ABT","company":"Abbott Laboratories","sector":"Healthcare","current_price":90.49,"change_pct":-0.04,"avg_volume":14043277,"scores":{"technical":29,"fundamental":37,"news":0,"composite":27,"mid_term":31},"trade":{"entry":90.49,"stop_loss":83.8448,"stop_pct":7.3,"target_1":92.73,"target_1_pct":2.5,"target_2":94.79,"target_2_pct":4.8,"risk_reward_t1":0.3,"risk_reward_t2":0.6},"indicators":{"rsi":54.2,"above_sma20":true,"above_sma50":true,"macd_bullish":true,"atr":2.2151,"atr_pct":2.45},"fundamentals":{"pe_ratio":25.34734,"revenue_growth":0.078,"profit_margin":0.13904999,"analyst_target":116.5417,"analyst_consensus":1.66667},"patterns":["Double Bottom"],"52w_high":138.84,"52w_low":81.97,"short_squeeze":false,"short_float_pct":1.4},{"ticker":"UNH","company":"UnitedHealth Group Incorporated","sector":"Healthcare","current_price":405.8,"change_pct":-0.84,"avg_volume":7144783,"scores":{"technical":31,"fundamental":30,"news":0,"composite":25,"mid_term":27},"trade":{"entry":405.8,"stop_loss":376.0699,"stop_pct":7.3,"target_1":415.98,"target_1_pct":2.5,"target_2":485.0802,"target_2_pct":19.5,"risk_reward_t1":0.3,"risk_reward_t2":2.7},"indicators":{"rsi":61.2,"above_sma20":true,"above_sma50":true,"macd_bullish":false,"atr":9.91,"atr_pct":2.44},"fundamentals":{"pe_ratio":30.603317,"revenue_growth":0.02,"profit_margin":0.02678,"analyst_target":409.7692,"analyst_consensus":1.64286},"patterns":["Bull Flag"],"52w_high":415.98,"52w_low":234.6,"short_squeeze":false,"short_float_pct":2.4},{"ticker":"ABBV","company":"AbbVie Inc.","sector":"Healthcare","current_price":234.89,"change_pct":0.06,"avg_volume":5993193,"scores":{"technical":61,"fundamental":12,"news":0,"composite":34,"mid_term":26},"trade":{"entry":234.89,"stop_loss":216.9741,"stop_pct":7.6,"target_1":244.81,"target_1_pct":4.2,"target_2":282.6657,"target_2_pct":20.3,"risk_reward_t1":0.6,"risk_reward_t2":2.7},"indicators":{"rsi":66.1,"above_sma20":true,"above_sma50":true,"macd_bullish":true,"atr":5.972,"atr_pct":2.54},"fundamentals":{"pe_ratio":115.14216,"revenue_growth":0.124,"profit_margin":0.05786,"analyst_target":253.8276,"analyst_consensus":1.75},"patterns":[],"52w_high":244.81,"52w_low":181.73,"short_squeeze":false,"short_float_pct":1.5},{"ticker":"GILD","company":"Gilead Sciences, Inc.","sector":"Healthcare","current_price":125.16,"change_pct":0.09,"avg_volume":9088921,"scores":{"technical":-61,"fundamental":70,"news":0,"composite":-7,"mid_term":21},"trade":{"entry":125.16,"stop_loss":114.8875,"stop_pct":8.2,"target_1":127.68,"target_1_pct":2.0,"target_2":128.2,"target_2_pct":2.4,"risk_reward_t1":0.2,"risk_reward_t2":0.3},"indicators":{"rsi":43.9,"above_sma20":false,"above_sma50":false,"macd_bullish":true,"atr":3.4242,"atr_pct":2.74},"fundamentals":{"pe_ratio":17.028572,"revenue_growth":0.044,"profit_margin":0.30993,"analyst_target":157.5714,"analyst_consensus":1.66667},"patterns":[],"52w_high":157.29,"52w_low":104.46,"short_squeeze":false,"short_float_pct":2.1},{"ticker":"ZTS","company":"Zoetis Inc.","sector":"Healthcare","current_price":78.17,"change_pct":1.73,"avg_volume":7195664,"scores":{"technical":-45,"fundamental":58,"news":0,"composite":-3,"mid_term":19},"trade":{"entry":78.17,"stop_loss":69.6282,"stop_pct":10.9,"target_1":82.34,"target_1_pct":5.3,"target_2":82.98,"target_2_pct":6.2,"risk_reward_t1":0.5,"risk_reward_t2":0.6},"indicators":{"rsi":40.3,"above_sma20":false,"above_sma50":false,"macd_bullish":true,"atr":2.8473,"atr_pct":3.64},"fundamentals":{"pe_ratio":12.814754,"revenue_growth":0.029,"profit_margin":0.28035,"analyst_target":124.5882,"analyst_consensus":2.05},"patterns":["MACD Bullish Divergence"],"52w_high":161.77,"52w_low":72.38,"short_squeeze":false,"short_float_pct":3.6},{"ticker":"BMY","company":"Bristol-Myers Squibb Company","sector":"Healthcare","current_price":55.0,"change_pct":-0.95,"avg_volume":13997521,"scores":{"technical":-33,"fundamental":48,"news":0,"composite":-1,"mid_term":17},"trade":{"entry":55.0,"stop_loss":50.8749,"stop_pct":7.5,"target_1":56.12,"target_1_pct":2.0,"target_2":56.97,"target_2_pct":3.6,"risk_reward_t1":0.3,"risk_reward_t2":0.5},"indicators":{"rsi":44.1,"above_sma20":false,"above_sma50":false,"macd_bullish":false,"atr":1.375,"atr_pct":2.5},"fundamentals":{"pe_ratio":15.406163,"revenue_growth":0.026,"profit_margin":0.15006,"analyst_target":63.08,"analyst_consensus":null},"patterns":["Double Bottom"],"52w_high":62.89,"52w_low":42.52,"short_squeeze":false,"short_float_pct":1.9},{"ticker":"MRNA","company":"Moderna, Inc.","sector":"Healthcare","current_price":60.42,"change_pct":-0.95,"avg_volume":7310169,"scores":{"technical":50,"fundamental":-15,"news":0,"composite":20,"mid_term":7},"trade":{"entry":60.42,"stop_loss":48.1401,"stop_pct":20.3,"target_1":67.74,"target_1_pct":12.1,"target_2":93.1663,"target_2_pct":54.2,"risk_reward_t1":0.6,"risk_reward_t2":2.7},"indicators":{"rsi":64.2,"above_sma20":true,"above_sma50":true,"macd_bullish":true,"atr":4.0933,"atr_pct":6.77},"fundamentals":{"pe_ratio":null,"revenue_growth":2.602,"profit_margin":-1.4355099,"analyst_target":43.45,"analyst_consensus":3.0},"patterns":["Golden Cross"],"52w_high":67.74,"52w_low":22.28,"short_squeeze":false,"short_float_pct":17.8},{"ticker":"PFE","company":"Pfizer Inc.","sector":"Healthcare","current_price":24.04,"change_pct":-2.75,"avg_volume":44104251,"scores":{"technical":-33,"fundamental":28,"news":0,"composite":-7,"mid_term":6},"trade":{"entry":24.04,"stop_loss":22.3235,"stop_pct":7.1,"target_1":24.8,"target_1_pct":3.2,"target_2":24.89,"target_2_pct":3.5,"risk_reward_t1":0.4,"risk_reward_t2":0.5},"indicators":{"rsi":27.8,"above_sma20":false,"above_sma50":false,"macd_bullish":false,"atr":0.5722,"atr_pct":2.38},"fundamentals":{"pe_ratio":18.351147,"revenue_growth":0.054,"profit_margin":0.118310004,"analyst_target":29.1507,"analyst_consensus":2.41379},"patterns":["Double Bottom"],"52w_high":28.75,"52w_low":23.11,"short_squeeze":false,"short_float_pct":2.8},{"ticker":"HUM","company":"Humana Inc.","sector":"Healthcare","current_price":361.64,"change_pct":0.7,"avg_volume":1443213,"scores":{"technical":61,"fundamental":-27,"news":0,"composite":22,"mid_term":4},"trade":{"entry":361.64,"stop_loss":326.4058,"stop_pct":9.7,"target_1":380.86,"target_1_pct":5.3,"target_2":455.598,"target_2_pct":26.0,"risk_reward_t1":0.5,"risk_reward_t2":2.7},"indicators":{"rsi":68.7,"above_sma20":true,"above_sma50":true,"macd_bullish":false,"atr":11.7447,"atr_pct":3.25},"fundamentals":{"pe_ratio":38.59552,"revenue_growth":0.235,"profit_margin":0.00824,"analyst_target":301.625,"analyst_consensus":2.57692},"patterns":["Bull Flag","Double Bottom"],"52w_high":380.86,"52w_low":163.11,"short_squeeze":false,"short_float_pct":5.8},{"ticker":"ISRG","company":"Intuitive Surgical, Inc.","sector":"Healthcare","current_price":401.83,"change_pct":-0.33,"avg_volume":2629702,"scores":{"technical":-69,"fundamental":44,"news":0,"composite":-20,"mid_term":3},"trade":{"entry":401.83,"stop_loss":366.2278,"stop_pct":8.9,"target_1":422.46,"target_1_pct":5.1,"target_2":430.85,"target_2_pct":7.2,"risk_reward_t1":0.6,"risk_reward_t2":0.8},"indicators":{"rsi":38.3,"above_sma20":false,"above_sma50":false,"macd_bullish":false,"atr":11.8674,"atr_pct":2.95},"fundamentals":{"pe_ratio":48.884426,"revenue_growth":0.23,"profit_margin":0.28152,"analyst_target":565.0786,"analyst_consensus":1.93939},"patterns":["MACD Bullish Divergence"],"52w_high":603.88,"52w_low":396.68,"short_squeeze":false,"short_float_pct":2.1}]}